CHANGES.rst
MANIFEST.in
README.rst
development.ini
message-extraction.ini
setup.cfg
setup.py
test.ini
belt/__init__.py
belt/axle.py
belt/models.py
belt/pshell.py
belt/utils.py
belt/values.py
belt/views.py
belt.egg-info/PKG-INFO
belt.egg-info/SOURCES.txt
belt.egg-info/dependency_links.txt
belt.egg-info/entry_points.txt
belt.egg-info/not-zip-safe
belt.egg-info/requires.txt
belt.egg-info/top_level.txt
belt/locale/circle.pot
belt/scripts/__init__.py
belt/scripts/createwheels.py
belt/scripts/initializedb.py
belt/scripts/pipcache.py
belt/static/favicon.ico
belt/static/logo.png
belt/static/pylons.css
belt/static/robots.txt
belt/templates/package_list.html
belt/templates/simple.html
belt/tests/__init__.py
belt/tests/conftest.py
belt/tests/test_axle.py
belt/tests/test_models.py
belt/tests/test_package_utils.py
belt/tests/test_views.py