Metadata-Version: 1.1
Name: belt
Version: 0.5
Summary: belt
Home-page: UNKNOWN
Author: Rob Berry
Author-email: UNKNOWN
License: BSD
Keywords: web wsgi bfg pylons pyramid
Platform: UNKNOWN
Classifier: Programming Language :: Python
Classifier: Framework :: Pyramid
Classifier: License :: OSI Approved :: BSD License
Classifier: Topic :: Internet :: WWW/HTTP
Classifier: Topic :: Internet :: WWW/HTTP :: WSGI :: Application
